Somendra_STT/__init__.py
Somendra_STT-1.0.dist-info/METADATA
Somendra_STT-1.0.dist-info/WHEEL
Somendra_STT-1.0.dist-info/top_level.txt
Somendra_STT-1.0.dist-info/RECORD
