Metadata-Version: 2.1
Name: Somendra_STT
Version: 1.0
Summary: This Speech To Text Module is developed by SOMENDRA KUMAR YADAV
Author: Somendra Kumar Yadav
Author-email: ysomendra901@gmail.com
